impress/__init__.py
impress/plane.py
impress/preprocessor.py
impress/setup.py
impress/vol_test.py
impress/preprocessor/__init__.py
impress/preprocessor/CythonUtil/__init__.py
impress/preprocessor/geoUtil/__init__.py
impress/preprocessor/geoUtil/geoTools.py
impress/preprocessor/geoUtil/geo_adjacencies.py
impress/preprocessor/meshHandle/__init__.py
impress/preprocessor/meshHandle/corePymoab.py
impress/preprocessor/meshHandle/dualCoarseMesh.py
impress/preprocessor/meshHandle/finescaleMesh.py
impress/preprocessor/meshHandle/meshComponents.py
impress/preprocessor/meshHandle/meshComponentsMS.py
impress/preprocessor/meshHandle/mscorePymoab.py
impress/preprocessor/meshHandle/multiscaleMesh.py
impress/preprocessor/meshHandle/configTools/__init__.py
impress/preprocessor/meshHandle/configTools/configClass.py
impress/preprocessor/msCoarseningLib/__init__.py
impress/preprocessor/msCoarseningLib/algoritmo.py
impress/preprocessor/msCoarseningLib/partitionTools.py
impress/testing_tools/__init__.py
impress/testing_tools/view.py
impress/tests/__init__.py
impress/tests/test_mesh_preprocessor.py
impress_padmec-1.7.0.dist-info/LICENSE
impress_padmec-1.7.0.dist-info/METADATA
impress_padmec-1.7.0.dist-info/WHEEL
impress_padmec-1.7.0.dist-info/top_level.txt
impress_padmec-1.7.0.dist-info/RECORD
