Metadata-Version: 2.1
Name: impress-padmec
Version: 1.7.0
Summary: Intuitive Multilevel Preprocessor for Smart Simulation
Home-page: https://github.com/padmec-reservoir/impress
Author: Artur Castiel, Gabriel Mendes
License: UNKNOWN
Platform: UNKNOWN
Requires-Python: >=3.6
Requires-Dist: ipython
Requires-Dist: pyyaml
Requires-Dist: numba
Requires-Dist: scipy
Requires-Dist: XlsxWriter (==1.1.2)
Requires-Dist: hdmedians
Requires-Dist: pytest
